{
    "name": "libmcpp",
    "type": "library",
    "deployConfig": "",
    "version": "1.2.14",
    "license": "",
    "description": "",
    "dependencies": {
        "test": [
            {
                "conan": "skynet/[>=1.8.0]@openubmc/stable"
            },
            {
                "conan": "json/b003_00004@openubmc/stable"
            }
        ],
        "build": [
            {
                "conan": "boost/[>=1.87.0.b003]@openubmc/stable"
            },
            {
                "conan": "libsomp/[>=1.80.9]@openubmc/stable"
            },
            {
                "conan": "liblogger/[>=1.90.0]@openubmc/stable"
            },
            {
                "conan": "skynet/[>=1.8.0]@openubmc/stable"
            },
            {
                "conan": "json/b003_00004@openubmc/stable"
            }
        ]
    },
    "required": []
}